setup.cfg
setup.py
flask_react/__init__.py
flask_react/config.py
flask_react/main.py
flask_react/worker.py
flask_react.egg-info/PKG-INFO
flask_react.egg-info/SOURCES.txt
flask_react.egg-info/dependency_links.txt
flask_react.egg-info/entry_points.txt
flask_react.egg-info/requires.txt
flask_react.egg-info/top_level.txt