Metadata-Version: 1.1
Name: flask-react
Version: 0.0.5
Summary: Auto setup tool for flask and react project
Home-page: https://github.com/ripitrust/flask_react.git
Author: chrimmme
Author-email: ripitrust@gmail.com
License: UNKNOWN
Download-URL: https://github.com/ripitrust/flask_react/tarball/0.0.5
Platform: UNKNOWN
